portfoliotools/__init__.py
portfoliotools/analytics/__init__.py
portfoliotools/analytics/constant.py
portfoliotools/analytics/portfolio_analytics.py
portfoliotools/screener/__init__.py
portfoliotools/screener/mutual_fund_screener.py
portfoliotools/screener/option_screener.py
portfoliotools/screener/screener_pattern.py
portfoliotools/screener/stock_detail.py
portfoliotools/screener/stock_fundamentals.py
portfoliotools/screener/stock_screener.py
portfoliotools/screener/strategy_screener.py
portfoliotools/screener/utility/__init__.py
portfoliotools/screener/utility/constant.py
portfoliotools/screener/utility/util.py
portfoliotools-2.2.9.dist-info/LICENSE
portfoliotools-2.2.9.dist-info/METADATA
portfoliotools-2.2.9.dist-info/WHEEL
portfoliotools-2.2.9.dist-info/top_level.txt
portfoliotools-2.2.9.dist-info/RECORD
