Metadata-Version: 2.1
Name: portfoliotools
Version: 2.2.9
Summary: Utils to fetch and analyze portoflio of stocks, index, mutual funds
Home-page: https://github.com/rahulspsec/portfoliotools/
Author: Rahul Jain
Author-email: rahulspsec@gmail.com
License: UNKNOWN
Platform: UNKNOWN
Classifier: Development Status :: 5 - Production/Stable
Classifier: Intended Audience :: Developers
Classifier: Intended Audience :: Financial and Insurance Industry
Classifier: Topic :: Office/Business :: Financial :: Investment
Classifier: Topic :: Software Development :: Libraries :: Python Modules
Classifier: Operating System :: OS Independent
Classifier: License :: OSI Approved :: MIT License
Classifier: Programming Language :: Python :: 3.7
Requires-Python: >=3.6
License-File: LICENSE
Requires-Dist: beautifulsoup4
Requires-Dist: pandas
Requires-Dist: numpy
Requires-Dist: mftool
Requires-Dist: requests
Requires-Dist: pandas-datareader
Requires-Dist: plotly
Requires-Dist: stocktrends
Requires-Dist: scipy
Requires-Dist: scikit-learn
Requires-Dist: seaborn
Requires-Dist: statsmodels
Requires-Dist: nsepy
Requires-Dist: nsetools
Requires-Dist: yfinance
Requires-Dist: nsepython
